LICENSE
MANIFEST.in
README.md
setup.py
apercal/__init__.py
apercal/exceptions.py
apercal.egg-info/PKG-INFO
apercal.egg-info/SOURCES.txt
apercal.egg-info/dependency_links.txt
apercal.egg-info/requires.txt
apercal.egg-info/top_level.txt
apercal/ao_strategies/__init__.py
apercal/ao_strategies/fluxcal.rfis
apercal/ao_strategies/fluxcal_apertif_XX.rfis
apercal/ao_strategies/fluxcal_nobp.rfis
apercal/ao_strategies/polcal.rfis
apercal/ao_strategies/polcal_nobp.rfis
apercal/ao_strategies/target.rfis
apercal/ao_strategies/target_apertif_XX.rfis
apercal/ao_strategies/target_nobp.rfis
apercal/libs/__init__.py
apercal/libs/calculations.py
apercal/libs/lib.py
apercal/modules/__init__.py
apercal/modules/base.py
apercal/modules/ccal.py
apercal/modules/continuum.py
apercal/modules/convert.py
apercal/modules/default.cfg
apercal/modules/line.py
apercal/modules/line_parallel.py
apercal/modules/mosaic.py
apercal/modules/polarisation.py
apercal/modules/preflag.py
apercal/modules/prepare.py
apercal/modules/scal.py
apercal/modules/transfer.py
apercal/pipeline/__init__.py
apercal/pipeline/start_pipeline.py
apercal/subs/__init__.py
apercal/subs/bandpass.py
apercal/subs/calmodels.py
apercal/subs/combim.py
apercal/subs/convim.py
apercal/subs/getdata_alta.py
apercal/subs/imstats.py
apercal/subs/irods.py
apercal/subs/lsm.py
apercal/subs/managefiles.py
apercal/subs/managetmp.py
apercal/subs/masking.py
apercal/subs/misc.py
apercal/subs/msutils.py
apercal/subs/param.py
apercal/subs/pb.py
apercal/subs/peeling.py
apercal/subs/qa.py
apercal/subs/readmirhead.py
apercal/subs/readmirlog.py
apercal/subs/setinit.py
test/test_ccal.py
test/test_continuum.py
test/test_convert.py
test/test_line.py
test/test_mosaic.py
test/test_preflag.py
test/test_prepare.py
test/test_scal.py
test/test_transfer.py